brainvistools/__init__.py
brainvistools/cbar.py
brainvistools/cmap.py
brainvistools/constants.py
brainvistools/freesurfer.py
brainvistools/networks.py
brainvistools/surface.py
brainvistools/timeseries.py
brainvistools/volume.py
brainvistools-0.0.2.dist-info/LICENCE
brainvistools-0.0.2.dist-info/METADATA
brainvistools-0.0.2.dist-info/WHEEL
brainvistools-0.0.2.dist-info/top_level.txt
brainvistools-0.0.2.dist-info/RECORD
