Metadata-Version: 2.1
Name: brainvistools
Version: 0.0.2
Summary: Plotting utilities for brain visualization
Home-page: https://git.bihealth.org/martinl/brainvistools
Author: Leon Martin
Author-email: leon.martin@bih-charite.de
License: UNKNOWN
Project-URL: Bug Tracker, https://git.bihealth.org/martinl/brainvistools/issues
Platform: UNKNOWN
Classifier: Programming Language :: Python :: 3
Classifier: Programming Language :: Python :: 3.9
Classifier: License :: OSI Approved :: MIT License
Classifier: Operating System :: OS Independent
Requires-Python: >=3.6
License-File: LICENCE
Requires-Dist: hcp-utils
Requires-Dist: matplotlib
Requires-Dist: mayavi
Requires-Dist: networkx
Requires-Dist: nibabel
Requires-Dist: nilearn
Requires-Dist: nltools
Requires-Dist: numpy
Requires-Dist: pandas
Requires-Dist: pysurfer
Requires-Dist: surfer
